{
  "code": "diy",
  "credit": "",
  "dimensions": [
    {
      "label": "进取心",
      "score": "100%"
    },
    {
      "label": "自我稳定",
      "score": "38%"
    },
    {
      "label": "亲密需求",
      "score": "75%"
    },
    {
      "label": "防御半径",
      "score": "80%"
    },
    {
      "label": "掌控欲",
      "score": "83%"
    },
    {
      "label": "清醒度",
      "score": "60%"
    }
  ],
  "imageSrc": "",
  "name": "我自己来型",
  "note": "代表瞬间：同事说\"这个我来吧\"，你微笑着点头，回到工位后默默把他交的版本重做了一遍。",
  "resultDesc": "\"算了我自己来\"是你这辈子说得最多的一句话。你不是不会求助，你是算过了——解释的时间够你做完三遍。你的人生信条是\"能自己搞定的事绝不麻烦别人，能麻烦别人的事也尽量自己搞定\"。累吗？累。但是看着别人把事情搞砸你更累。"
}
